nicelogger.py
nicelogger-2.0.dist-info/METADATA
nicelogger-2.0.dist-info/RECORD
nicelogger-2.0.dist-info/WHEEL
nicelogger-2.0.dist-info/top_level.txt
